rcsb/__init__.py
rcsb/ccmodels/__init__.py
rcsb/ccmodels/search/CcdcSearchExecMp.py
rcsb/ccmodels/search/ChemCompModelAssemble.py
rcsb/ccmodels/search/ChemCompModelBuild.py
rcsb/ccmodels/search/ChemCompModelExec.py
rcsb/ccmodels/search/ChemCompModelGen.py
rcsb/ccmodels/search/ChemCompModelSearch.py
rcsb/ccmodels/search/__init__.py
rcsb/ccmodels/tests/__init__.py
rcsb/ccmodels/tests/testChemCompModelGen.py
rcsb/ccmodels/tests/testChemCompModelSearch.py
rcsb/ccmodels/tests/testXChemCompModelBuild.py
rcsb/ccmodels/tests/testYChemCompModelAssemble.py
rcsb.ccmodels-0.23.dist-info/LICENSE
rcsb.ccmodels-0.23.dist-info/METADATA
rcsb.ccmodels-0.23.dist-info/WHEEL
rcsb.ccmodels-0.23.dist-info/dependency_links.txt
rcsb.ccmodels-0.23.dist-info/entry_points.txt
rcsb.ccmodels-0.23.dist-info/top_level.txt
rcsb.ccmodels-0.23.dist-info/RECORD
